README
setup.py
wayround_org/sasl/__init__.py
wayround_org/sasl/sasl.py
wayround_org_sasl.egg-info/PKG-INFO
wayround_org_sasl.egg-info/SOURCES.txt
wayround_org_sasl.egg-info/dependency_links.txt
wayround_org_sasl.egg-info/top_level.txt