Metadata-Version: 1.1
Name: wayround-org-sasl
Version: 0.1
Summary: pure python sasl mechanisms realisation
Home-page: https://github.com/AnimusPEXUS/wayround_org_sasl
Author: Alexey Gorshkov
Author-email: animus@wayround.org
License: UNKNOWN
Platform: UNKNOWN
Classifier: License :: OSI Approved :: GNU General Public License v3 or later (GPLv3+)
